README.md
setup.py
test_lasa/__init__.py
test_lasa.egg-info/PKG-INFO
test_lasa.egg-info/SOURCES.txt
test_lasa.egg-info/dependency_links.txt
test_lasa.egg-info/entry_points.txt
test_lasa.egg-info/requires.txt
test_lasa.egg-info/top_level.txt